highlights/__init__.py
highlights/admin.py
highlights/apps.py
highlights/migrations/0001_initial.py
highlights/migrations/__init__.py
highlights/models.py
highlights/static/img/favicons/android-chrome-192x192.png
highlights/static/img/favicons/android-chrome-512x512.png
highlights/static/img/favicons/apple-touch-icon.png
highlights/static/img/favicons/favicon-16x16.png
highlights/static/img/favicons/favicon-32x32.png
highlights/static/img/favicons/favicon.ico
highlights/static/img/favicons/site.webmanifest
highlights/static/js/removeSelected.js
highlights/static/js/textSelector.js
highlights/templates/_favicons.html
highlights/templates/_messages.html
highlights/templates/_nav.html
highlights/templates/base.html
highlights/templates/highlights/footer.html
highlights/templatetags/__init__.py
highlights/templatetags/highlighter.py
highlights/tests.py
highlights/urls.py
highlights/views.py
django_highlights-0.0.8.dist-info/WHEEL
django_highlights-0.0.8.dist-info/METADATA
django_highlights-0.0.8.dist-info/RECORD
