Metadata-Version: 2.1
Name: django-highlights
Version: 0.0.8
Summary: Text selection and save as highlight via htmx
Home-page: https://github.com/justmars/django-highlights
License: MIT
Author: Marcelino G. Veloso III
Author-email: mars@veloso.one
Requires-Python: >=3.8,<4.0
Classifier: License :: OSI Approved :: MIT License
Classifier: Programming Language :: Python :: 3
Classifier: Programming Language :: Python :: 3.8
Classifier: Programming Language :: Python :: 3.9
Classifier: Programming Language :: Python :: 3.10
Requires-Dist: Django (>=4.0,<5.0)
Requires-Dist: django-debug-toolbar (>=3.2.2,<4.0.0)
Requires-Dist: django-extensions (>=3.1.5,<4.0.0)
Project-URL: Repository, https://github.com/justmars/django-highlights
